vetox/__init__.py
vetox/__main__.py
vetox-0.2.1.dist-info/METADATA
vetox-0.2.1.dist-info/WHEEL
vetox-0.2.1.dist-info/entry_points.txt
vetox-0.2.1.dist-info/licenses/LICENSES/BSD-2-Clause.txt
vetox-0.2.1.dist-info/RECORD
