Metadata-Version: 2.4
Name: vetox
Version: 0.2.1
Summary: Create a virtual environment, install Tox, run it
Project-URL: Homepage, https://devel.ringlet.net/devel/vetox/
Project-URL: Changes, https://devel.ringlet.net/devel/vetox/changes/
Project-URL: Issue Tracker, https://gitlab.com/ppentchev/vetox/-/issues
Project-URL: Source Code, https://gitlab.com/ppentchev/vetox
Author-email: Peter Pentchev <roam@ringlet.net>
License-Expression: BSD-2-Clause
License-File: LICENSES/BSD-2-Clause.txt
Classifier: Development Status :: 5 - Production/Stable
Classifier: Intended Audience :: Developers
Classifier: Operating System :: OS Independent
Classifier: Programming Language :: Python
Classifier: Programming Language :: Python :: 3
Classifier: Programming Language :: Python :: 3 :: Only
Classifier: Programming Language :: Python :: 3.9
Classifier: Programming Language :: Python :: 3.10
Classifier: Programming Language :: Python :: 3.11
Classifier: Programming Language :: Python :: 3.12
Classifier: Programming Language :: Python :: 3.13
Classifier: Programming Language :: Python :: 3.14
Classifier: Topic :: Software Development :: Libraries
Classifier: Topic :: Software Development :: Libraries :: Python Modules
Classifier: Topic :: Software Development :: Testing
Classifier: Topic :: Software Development :: Testing :: Unit
Classifier: Typing :: Typed
Requires-Python: >=3.9
